compressedcrack/__init__.py
compressedcrack/main.py
compressedcrack-1.0.3.dist-info/LICENSE
compressedcrack-1.0.3.dist-info/METADATA
compressedcrack-1.0.3.dist-info/WHEEL
compressedcrack-1.0.3.dist-info/entry_points.txt
compressedcrack-1.0.3.dist-info/top_level.txt
compressedcrack-1.0.3.dist-info/RECORD
