Metadata-Version: 2.1
Name: compressedcrack
Version: 1.0.3
Summary: A command-line tool to crack password-protected compressed files using brute force.
Home-page: https://github.com/mnismt/CompressedCrack
Author: Minh Thanh
Author-email: Minh Thanh <thanhdoantranminh@gmail.com>
License: MIT License
Project-URL: Homepage, https://github.com/mnismt/CompressedCrack
Project-URL: Bug Tracker, https://github.com/mnismt/CompressedCrack/issues
Keywords: brute force,password cracking,compressed files
Classifier: Development Status :: 3 - Alpha
Classifier: Intended Audience :: Developers
Classifier: License :: OSI Approved :: MIT License
Classifier: Programming Language :: Python :: 3
Classifier: Programming Language :: Python :: 3.6
Classifier: Programming Language :: Python :: 3.7
Classifier: Programming Language :: Python :: 3.8
Classifier: Programming Language :: Python :: 3.9
Requires-Python: >=3.6
License-File: LICENSE
Requires-Dist: patool >=2.2.0
